{"name":"Picklist","tagline":"A simple PickList using jQuery and Bootstrap","body":"![pickList is a simple plugin for jQuery.](http://s9.postimg.org/li46m3gvj/pick_List.png)\r\n\r\n<h2>\r\n<a name=\"installation\" class=\"anchor\" href=\"#installation\"><span class=\"mini-icon mini-icon-link\"></span></a>Installation</h2>\r\n\r\n<p>Include script <em>after</em> the jQuery library:</p>\r\n\r\n<pre><code>&lt;script src=\"pickList.js\"&gt;&lt;/script&gt;\r\n</code></pre>\r\n\r\n\r\n<h2>\r\n<a name=\"usage\" class=\"anchor\" href=\"#usage\"><span class=\"mini-icon mini-icon-link\"></span></a>Usage</h2>\r\n\r\n<p>Basic setup:</p>\r\n\r\n```html\r\n<div id=\"pickList\"></div>  <!-- HTML -->\r\n```\r\n\r\n```javascript\r\n$(\"#pickList\").pickList(); // JS\r\n```\r\n<p>To set data into the plugin just include:</p>\r\n```javascript\r\nvar val = {\r\n    01: {id: 01, text: 'Isis'},\r\n    02: {id: 02, text: 'Sophia'},\r\n    03: {id: 03, text: 'Alice'},\r\n    04: {id: 04, text: 'Isabella'},\r\n    05: {id: 05, text: 'Manuela'},\r\n    06: {id: 06, text: 'Laura'}\r\n  };\r\n\r\nvar pick = $(\"#pickList\").pickList({data: val});\r\n```\r\n<p>To get data just call the getValues:</p>\r\n```javascript\r\n var pick = $(\"#pickList\").pickList({data: val});\r\n\r\n $(\"#getSelected\").click(function () {\r\n     console.log(pick.getValues());\r\n });\r\n```\r\n<h2>\r\n<a name=\"demo\" class=\"anchor\" href=\"#demo\"><span class=\"mini-icon mini-icon-link\"></span></a>Demo</h2>\r\n<p><strong><a href=\"https://jsfiddle.net/filadown/8ek53b1f/\">pickList Jsfiddle Show + Code</a></strong> </p>\r\n<p><strong><a href=\"https://jsfiddle.net/filadown/8ek53b1f/show\">pickList Jsfiddle Show</a></strong> </p>\r\n<h2>\r\n<a name=\"authors\" class=\"anchor\" href=\"#authors\"><span class=\"mini-icon mini-icon-link\"></span></a>Author</h2>\r\n\r\n<p><a href=\"http://pt.stackoverflow.com/users/17658/gabriel-rodrigues\" target=\"_blank\">Gabriel Rodrigues</a></p>\r\n\r\n","google":"","note":"Don't delete this file! It's used internally to help with page regeneration."}